{"version": 0.6, "generator": "Overpass API 0.7.61.5 4133829e", "osm3s": {"timestamp_osm_base": "2023-09-27T02:04:36Z", "copyright": "The data included in this document is from www.openstreetmap.org. The data is made available under ODbL."}, "elements": [{"type": "node", "id": 320884370, "lat": 30.4744703, "lon": -97.7984686}, {"type": "node", "id": 320884371, "lat": 30.4745605, "lon": -97.7981668}, {"type": "node", "id": 320884372, "lat": 30.4743869, "lon": -97.7980969}, {"type": "node", "id": 320884373, "lat": 30.4742967, "lon": -97.7983988}, {"type": "node", "id": 4727762157, "lat": 30.4762517, "lon": -97.7981296, "tags": {"addr:city": "Austin", "addr:housenumber": "14005", "addr:postcode": "78717", "addr:state": "TX", "addr:street": "183A Toll Road", "addr:unit": "1000", "amenity": "restaurant", "cuisine": "sushi", "delivery": "yes", "description": "Currently NO dine-in due to COVID-19.", "diet:vegetarian": "yes", "name": "Sushi Bang Bang", "opening_hours": "Mo-Th 11:00-21:00; Fr-Su 11:00-21:30", "phone": "+1-512-609-8185", "reservation": "yes", "takeaway": "yes", "takeaway:covid19": "only", "website": "https://sushibangbangtx.com/", "wheelchair": "yes"}}, {"type": "node", "id": 7094945934, "lat": 30.4725247, "lon": -97.79697, "tags": {"addr:city": "Austin", "addr:housenumber": "13945", "addr:postcode": "78717", "addr:state": "TX", "addr:street": "Highway 183 North", "addr:unit": "C-5", "amenity": "restaurant", "cuisine": "indian", "diet:halal": "yes", "diet:vegetarian": "yes", "name": "Biryani-N-Grill", "opening_hours": "Mo-Su 11:00-22:00", "phone": "+1-512-879-4123", "takeaway": "yes", "website": "http://biryaningrill.com/north/", "wheelchair": "yes"}}, {"type": "node", "id": 8532169387, "lat": 30.4743369, "lon": -97.798415, "tags": {"entrance": "main"}}, {"type": "node", "id": 8532169389, "lat": 30.4745464, "lon": -97.7982161}, {"type": "node", "id": 8532169390, "lat": 30.4744812, "lon": -97.7984317}, {"type": "node", "id": 8534492026, "lat": 30.4760761, "lon": -97.7980547, "tags": {"addr:city": "Austin", "addr:housenumber": "14005", "addr:postcode": "78717", "addr:state": "TX", "addr:street": "183A Toll Road", "addr:unit": "600", "amenity": "restaurant", "bar": "yes", "cuisine": "chinese", "delivery": "yes", "diet:healthy": "yes", "diet:vegetarian": "yes", "name": "China Cafe", "opening_hours": "Mo-Su 11:00-22:00", "phone": "+1-512-331-7747", "safety:mask:covid19": "yes", "takeaway": "yes", "website": "https://www.chinacafelakeline.com/", "wheelchair": "yes"}}, {"type": "node", "id": 8534492028, "lat": 30.4757107, "lon": -97.7979403, "tags": {"addr:city": "Austin", "addr:housenumber": "14005", "addr:postcode": "78717", "addr:state": "TX", "addr:street": "183A Toll Road", "addr:unit": "500", "amenity": "restaurant", "brand": "First Watch", "brand:wikidata": "Q5454064", "brand:wikipedia": "en:First Watch (restaurant chain)", "cuisine": "american;breakfast", "delivery": "yes", "description": "Closes for Thanksgiving and Christmas.", "name": "First Watch", "official_name": "First Watch The Daytime Cafe", "opening_hours:covid19": "Mo-Su 07:00-14:30", "outdoor_seating": "yes", "phone": "+1-512-250-3447", "reservation": "yes", "safety:mask:covid19": "yes", "takeaway": "yes", "website": "https://www.firstwatch.com/locations/walden", "wheelchair": "yes"}}, {"type": "node", "id": 8534622952, "lat": 30.4767812, "lon": -97.7946427, "tags": {"addr:city": "Austin", "addr:housenumber": "10900", "addr:postcode": "78717", "addr:state": "TX", "addr:street": "Lakeline Mall Drive", "addr:unit": "650", "amenity": "restaurant", "delivery": "no", "diet:gluten_free": "yes", "diet:healthy": "yes", "diet:vegan": "yes", "diet:vegetarian": "yes", "name": "Nancy's Sky Garden", "opening_hours": "Mo-Su 11:00-20:30", "outdoor_seating": "yes", "phone": "+1-512-337-9030", "safety:mask:covid19": "yes", "takeaway": "yes", "website": "http://www.nancysskygarden.com/", "wheelchair": "yes"}}, {"type": "way", "id": 29177460, "nodes": [320884370, 8532169390, 8532169389, 320884371, 320884372, 320884373, 8532169387, 320884370], "tags": {"addr:city": "Austin", "addr:housenumber": "13995", "addr:postcode": "78717", "addr:state": "TX", "addr:street": "Research Boulevard", "amenity": "restaurant", "bar": "yes", "building": "yes", "cuisine": "regional", "email": "foxhole@foxholetavern.com", "name": "Foxhole Culinary Tavern", "opening_hours": "Mo-We 11:00-23:00; Th-Fr 11:00-24:00; Sa 10:00-24:00; Su 10:00-23:00", "opening_hours:covid19": "Mo-Fr 15:00-21:00; Sa-Su 10:00-21:00", "outdoor_seating": "yes", "phone": "+1-512-386-1354", "reservation": "yes", "takeaway": "yes", "website": "http://www.foxholeaustin.com/", "wheelchair": "yes"}}]}