{"version": 0.6, "generator": "Overpass API 0.7.61.5 4133829e", "osm3s": {"timestamp_osm_base": "2023-09-27T01:59:30Z", "copyright": "The data included in this document is from www.openstreetmap.org. The data is made available under ODbL."}, "elements": [{"type": "node", "id": 860386860, "lat": 30.3746805, "lon": -97.727753}, {"type": "node", "id": 860386861, "lat": 30.3744401, "lon": -97.7279094}, {"type": "node", "id": 860386862, "lat": 30.3743524, "lon": -97.7278707}, {"type": "node", "id": 860386863, "lat": 30.374367, "lon": -97.7277399}, {"type": "node", "id": 860386864, "lat": 30.3745998, "lon": -97.7275885}, {"type": "node", "id": 860386886, "lat": 30.3742917, "lon": -97.7269592}, {"type": "node", "id": 860386887, "lat": 30.3741907, "lon": -97.7270251}, {"type": "node", "id": 860386891, "lat": 30.3740212, "lon": -97.7266765}, {"type": "node", "id": 860386893, "lat": 30.3741222, "lon": -97.7266105}, {"type": "node", "id": 860386990, "lat": 30.3726468, "lon": -97.7231852}, {"type": "node", "id": 860386992, "lat": 30.3725524, "lon": -97.723245}, {"type": "node", "id": 860386994, "lat": 30.3725188, "lon": -97.7231736}, {"type": "node", "id": 860386995, "lat": 30.3723629, "lon": -97.7232723}, {"type": "node", "id": 860386996, "lat": 30.3723089, "lon": -97.7231577}, {"type": "node", "id": 860386998, "lat": 30.3723521, "lon": -97.7231303}, {"type": "node", "id": 860386999, "lat": 30.3723034, "lon": -97.7230271}, {"type": "node", "id": 860387000, "lat": 30.3725457, "lon": -97.7228737}, {"type": "node", "id": 860387002, "lat": 30.3725993, "lon": -97.7229873}, {"type": "node", "id": 860387006, "lat": 30.3725641, "lon": -97.7230096}, {"type": "node", "id": 860573218, "lat": 30.3707493, "lon": -97.7277138}, {"type": "node", "id": 860573219, "lat": 30.3706007, "lon": -97.7277835}, {"type": "node", "id": 860573220, "lat": 30.3704935, "lon": -97.7275023}, {"type": "node", "id": 860573221, "lat": 30.3706327, "lon": -97.7274195}, {"type": "node", "id": 1479713176, "lat": 30.3759961, "lon": -97.7263411, "tags": {"amenity": "fuel", "brand": "Texaco", "brand:wikidata": "Q775060", "brand:wikipedia": "en:Texaco", "name": "Texaco"}}, {"type": "node", "id": 1521404355, "lat": 30.3729305, "lon": -97.7241083, "tags": {"addr:housename": "Suite # 100", "addr:housenumber": "9025", "addr:postcode": "78758", "addr:street": "Research Boulevard", "amenity": "restaurant", "cuisine": "indian", "name": "Madras Pavilion", "phone": "+1-512-719-5575", "source": "local_knowledge", "website": "madraspavilion.us"}}, {"type": "node", "id": 1521404362, "lat": 30.3735916, "lon": -97.7254254, "tags": {"addr:housename": "Suite # 150", "addr:housenumber": "9041", "addr:postcode": "78758-7008", "addr:street": "Research Boulevard", "amenity": "restaurant", "cuisine": "thai", "name": "Thai House", "phone": "+1-512-832-9722", "source": "local_knowledge", "website": "http://www.thaihouseaustin.com"}}, {"type": "node", "id": 1521407218, "lat": 30.3734303, "lon": -97.7247091, "tags": {"addr:housenumber": "9033", "addr:postcode": "78758-7013", "addr:street": "Research Boulevard", "amenity": "restaurant", "cuisine": "japanese", "name": "Mikado Ryotei", "phone": "+1-512-833-8188", "source": "local_knowledge", "website": "mikadoryotei.com"}}, {"type": "node", "id": 2528868968, "lat": 30.3714622, "lon": -97.7277035, "tags": {"amenity": "car_rental", "name": "Avis/Budget"}}, {"type": "node", "id": 2528868982, "lat": 30.3723167, "lon": -97.7271869, "tags": {"amenity": "restaurant", "brand": "Chili's", "brand:wikidata": "Q1072948", "brand:wikipedia": "en:Chili's", "cuisine": "tex-mex", "name": "Chili's", "official_name": "Chili's Grill & Bar"}}, {"type": "node", "id": 2654876567, "lat": 30.3762593, "lon": -97.7285247}, {"type": "node", "id": 2654876570, "lat": 30.3763544, "lon": -97.7283919}, {"type": "node", "id": 2654876590, "lat": 30.376672, "lon": -97.7294874}, {"type": "node", "id": 2654876599, "lat": 30.376647, "lon": -97.7292787}, {"type": "node", "id": 2654876602, "lat": 30.3766838, "lon": -97.7295857}, {"type": "node", "id": 2654876614, "lat": 30.3768157, "lon": -97.7280944}, {"type": "node", "id": 2654876623, "lat": 30.3769098, "lon": -97.7294885}, {"type": "node", "id": 2654876651, "lat": 30.3771788, "lon": -97.7292384}, {"type": "node", "id": 2654876655, "lat": 30.3771808, "lon": -97.728386}, {"type": "node", "id": 2654876656, "lat": 30.3771849, "lon": -97.7282153}, {"type": "node", "id": 2654876665, "lat": 30.377276, "lon": -97.7290653}, {"type": "node", "id": 2654876670, "lat": 30.3773404, "lon": -97.7287677}, {"type": "node", "id": 2654876671, "lat": 30.3773475, "lon": -97.7283872}, {"type": "node", "id": 2654876674, "lat": 30.3773578, "lon": -97.7282188}, {"type": "node", "id": 2654876676, "lat": 30.3773598, "lon": -97.7280778}, {"type": "node", "id": 3163089574, "lat": 30.3710022, "lon": -97.7268143, "tags": {"amenity": "bench"}}, {"type": "node", "id": 3163089575, "lat": 30.3710236, "lon": -97.7268043, "tags": {"amenity": "waste_basket"}}, {"type": "node", "id": 3163670654, "lat": 30.3746585, "lon": -97.7258802, "tags": {"amenity": "bicycle_parking", "bicycle_parking": "stands"}}, {"type": "node", "id": 3163670655, "lat": 30.3746759, "lon": -97.7258778, "tags": {"amenity": "bench"}}, {"type": "node", "id": 3163670656, "lat": 30.3747031, "lon": -97.7258763, "tags": {"amenity": "waste_basket"}}, {"type": "node", "id": 3168596601, "lat": 30.3711242, "lon": -97.727056, "tags": {"amenity": "waste_basket"}}, {"type": "node", "id": 3168596603, "lat": 30.3711443, "lon": -97.7270508, "tags": {"amenity": "bench"}}, {"type": "node", "id": 3168596605, "lat": 30.3757611, "lon": -97.7259973, "tags": {"amenity": "waste_basket"}}, {"type": "node", "id": 3168596606, "lat": 30.3757664, "lon": -97.7259655}, {"type": "node", "id": 3168596607, "lat": 30.3757688, "lon": -97.7259887}, {"type": "node", "id": 3168596608, "lat": 30.3758062, "lon": -97.7259598}, {"type": "node", "id": 3168596609, "lat": 30.3758087, "lon": -97.725983}, {"type": "node", "id": 3930556075, "lat": 30.3767131, "lon": -97.7251189, "tags": {"amenity": "veterinary", "name": "Veterinary Surgical Solutions"}}, {"type": "node", "id": 5330344722, "lat": 30.3735638, "lon": -97.7255279, "tags": {"addr:housenumber": "9041", "addr:postcode": "78758", "addr:street": "Research Boulevard", "amenity": "restaurant", "cuisine": "mexican", "name": "Casa Chapala", "website": "https://www.casachapala.com"}}, {"type": "node", "id": 5591019630, "lat": 30.3733666, "lon": -97.7188715}, {"type": "node", "id": 5591019631, "lat": 30.372329, "lon": -97.7195328}, {"type": "node", "id": 7255870318, "lat": 30.3715088, "lon": -97.7245372, "tags": {"addr:city": "Austin", "addr:housenumber": "9012", "addr:postcode": "78758", "addr:state": "TX", "addr:street": "Research Boulevard", "air_conditioning": "yes", "amenity": "cafe", "indoor_seating": "yes", "name": "Emerald Tavern Games", "opening_hours": "Su 11:00-21:00; Mo off; Tu-Th 11:00-23:00; Fr,Sa 11:00-24:00", "outdoor_seating": "yes", "phone": "+1-512-994-4649", "website": "https://www.emeraldtaverngames.com/"}}, {"type": "node", "id": 9027460393, "lat": 30.3773583, "lon": -97.7281864}, {"type": "node", "id": 9179323833, "lat": 30.3736288, "lon": -97.7207751}, {"type": "node", "id": 9179323834, "lat": 30.3745996, "lon": -97.7212364}, {"type": "node", "id": 9179323835, "lat": 30.3747268, "lon": -97.721097}, {"type": "node", "id": 9179323836, "lat": 30.3748113, "lon": -97.7209776}, {"type": "node", "id": 9179323837, "lat": 30.3749015, "lon": -97.7207912}, {"type": "node", "id": 9179323838, "lat": 30.3742594, "lon": -97.7204733}, {"type": "node", "id": 9179323839, "lat": 30.3744283, "lon": -97.7199597}, {"type": "node", "id": 9179323840, "lat": 30.3744688, "lon": -97.7198377}, {"type": "node", "id": 9179323841, "lat": 30.3743774, "lon": -97.7198068}, {"type": "node", "id": 9179323842, "lat": 30.3742837, "lon": -97.7197639}, {"type": "node", "id": 9179323843, "lat": 30.3741749, "lon": -97.7197049}, {"type": "node", "id": 9179323844, "lat": 30.3740662, "lon": -97.7196351}, {"type": "node", "id": 9179323845, "lat": 30.3739458, "lon": -97.7195547}, {"type": "node", "id": 9179323846, "lat": 30.3738359, "lon": -97.7194635}, {"type": "node", "id": 9179323847, "lat": 30.3737434, "lon": -97.7193803}, {"type": "node", "id": 9179323848, "lat": 30.3736103, "lon": -97.7192167}, {"type": "node", "id": 9179323849, "lat": 30.3735177, "lon": -97.7190853}, {"type": "node", "id": 9179323850, "lat": 30.3734263, "lon": -97.7189136}, {"type": "node", "id": 9179323851, "lat": 30.3734009, "lon": -97.718856}, {"type": "node", "id": 9179323852, "lat": 30.372267, "lon": -97.7195721}, {"type": "node", "id": 9179323853, "lat": 30.3728038, "lon": -97.7204303}, {"type": "node", "id": 9179323854, "lat": 30.3732842, "lon": -97.7201315}, {"type": "node", "id": 9179323855, "lat": 30.3735894, "lon": -97.7207666}, {"type": "node", "id": 10876576985, "lat": 30.3711681, "lon": -97.7247135, "tags": {"addr:city": "Austin", "addr:housenumber": "9012", "addr:postcode": "78758", "addr:state": "TX", "addr:street": "Research Boulevard", "addr:unit": "C-6", "amenity": "restaurant", "cuisine": "mexican", "diet:vegan": "only", "name": "Nissi Vegan M\u00e9xican Cuisine", "opening_hours": "Mo-Sa 11:00-20:00", "website": "https://www.nissivegmex.com/"}}, {"type": "node", "id": 11108444382, "lat": 30.3725183, "lon": -97.7224688}, {"type": "node", "id": 11108444383, "lat": 30.372357, "lon": -97.7221287}, {"type": "node", "id": 11108444384, "lat": 30.3729414, "lon": -97.7217564}, {"type": "node", "id": 11108444385, "lat": 30.3731027, "lon": -97.7220967}, {"type": "node", "id": 11108444386, "lat": 30.3729324, "lon": -97.7217622}, {"type": "node", "id": 11108455197, "lat": 30.3759004, "lon": -97.7292606}, {"type": "node", "id": 11108455198, "lat": 30.3758796, "lon": -97.7292168}, {"type": "node", "id": 11108455199, "lat": 30.3758706, "lon": -97.7292225}, {"type": "node", "id": 11108455200, "lat": 30.3758406, "lon": -97.7291594}, {"type": "node", "id": 11108455201, "lat": 30.3758053, "lon": -97.729182}, {"type": "node", "id": 11108455202, "lat": 30.3756907, "lon": -97.7289408}, {"type": "node", "id": 11108455203, "lat": 30.376118, "lon": -97.728668}, {"type": "node", "id": 11108455204, "lat": 30.3761418, "lon": -97.728718}, {"type": "node", "id": 11108461605, "lat": 30.3762058, "lon": -97.7286772}, {"type": "node", "id": 11108461606, "lat": 30.3763474, "lon": -97.7289751}, {"type": "node", "id": 11108461672, "lat": 30.3763375, "lon": -97.7289814}, {"type": "node", "id": 11108461673, "lat": 30.3761661, "lon": -97.7290909}, {"type": "node", "id": 11108461683, "lat": 30.3759409, "lon": -97.7292347}, {"type": "way", "id": 72470353, "nodes": [860386860, 860386861, 860386862, 860386863, 860386864, 860386860], "tags": {"addr:housenumber": "9091", "addr:postcode": "78758", "addr:street": "Research Boulevard", "amenity": "restaurant", "building": "yes", "name": "Jim's Restaurant"}}, {"type": "way", "id": 72470358, "nodes": [860386886, 860386887, 860386891, 860386893, 860386886], "tags": {"addr:housenumber": "9061", "addr:postcode": "78758", "addr:street": "Research Boulevard", "amenity": "fuel", "brand": "Exxon", "brand:wikidata": "Q4781944", "brand:wikipedia": "en:Exxon", "building": "roof", "name": "Exxon"}}, {"type": "way", "id": 72470377, "nodes": [860386990, 860386992, 860386994, 860386995, 860386996, 860386998, 860386999, 860387000, 860387002, 860387006, 860386990], "tags": {"addr:housenumber": "8989", "addr:postcode": "78758", "addr:state": "TX", "addr:street": "Research Boulevard", "amenity": "fire_station", "building": "yes", "ele": "225", "gnis:county_name": "Travis", "gnis:feature_id": "2360685", "gnis:import_uuid": "57871b70-0100-4405-bb30-88b2e001a944", "gnis:reviewed": "no", "name": "Austin Fire Station Number 8", "source": "USGS Geonames"}}, {"type": "way", "id": 72491603, "nodes": [860573218, 860573219, 860573220, 860573221, 860573218], "tags": {"amenity": "restaurant", "building": "yes", "name": "Trudy's"}}, {"type": "way", "id": 260033810, "nodes": [2654876671, 2654876655, 2654876656, 2654876674, 9027460393, 2654876676, 2654876614, 2654876570, 2654876567, 2654876599, 2654876590, 2654876602, 2654876623, 2654876651, 2654876665, 2654876670, 2654876671], "tags": {"amenity": "parking"}}, {"type": "way", "id": 311260279, "nodes": [3168596609, 3168596607, 3168596606, 3168596608, 3168596609], "tags": {"amenity": "shelter", "bench": "yes", "shelter_type": "public_transport"}}, {"type": "way", "id": 993565445, "nodes": [9179323833, 9179323834, 9179323835, 9179323836, 9179323837, 9179323838, 9179323839, 9179323840, 9179323841, 9179323842, 9179323843, 9179323844, 9179323845, 9179323846, 9179323847, 9179323848, 9179323849, 9179323850, 9179323851, 5591019630, 5591019631, 9179323852, 9179323853, 9179323854, 9179323855, 9179323833], "tags": {"addr:city": "Austin", "addr:housenumber": "2011", "addr:postcode": "78758", "addr:state": "TX", "addr:street": "West Rundberg Lane", "amenity": "school", "grades": "k-5", "name": "Padr\u00f3n Elementary School", "operator": "Austin Independent School District", "operator:short": "AISD", "operator:type": "public", "operator:wikidata": "Q4823141", "website": "https://padron.austinschools.org/"}}, {"type": "way", "id": 1197182038, "nodes": [11108444382, 11108444383, 11108444386, 11108444384, 11108444385, 11108444382], "tags": {"amenity": "parking", "building": "construction", "parking": "multi-storey"}}, {"type": "way", "id": 1197184729, "nodes": [11108455197, 11108455198, 11108455199, 11108455200, 11108455201, 11108455202, 11108455203, 11108455204, 11108461605, 11108461606, 11108461672, 11108461673, 11108461683, 11108455197], "tags": {"amenity": "parking", "building": "construction", "parking": "multi-storey"}}]}