{"version": 0.6, "generator": "Overpass API 0.7.61.5 4133829e", "osm3s": {"timestamp_osm_base": "2023-09-27T02:02:36Z", "copyright": "The data included in this document is from www.openstreetmap.org. The data is made available under ODbL."}, "elements": [{"type": "node", "id": 599493152, "lat": 30.4001039, "lon": -97.748023, "tags": {"amenity": "restaurant", "cuisine": "chinese", "name": "Twin Lion"}}, {"type": "node", "id": 599493162, "lat": 30.3988329, "lon": -97.7490667, "tags": {"amenity": "restaurant", "cuisine": "italian", "name": "Brick Oven"}}, {"type": "node", "id": 859657438, "lat": 30.3968503, "lon": -97.7494366}, {"type": "node", "id": 859657439, "lat": 30.3967206, "lon": -97.749448}, {"type": "node", "id": 859657441, "lat": 30.396716, "lon": -97.7493789}, {"type": "node", "id": 859657446, "lat": 30.3965808, "lon": -97.749356}, {"type": "node", "id": 859657447, "lat": 30.3965735, "lon": -97.7492444}, {"type": "node", "id": 859657449, "lat": 30.3967025, "lon": -97.749233}, {"type": "node", "id": 859657450, "lat": 30.3966987, "lon": -97.7491744}, {"type": "node", "id": 859657451, "lat": 30.3968323, "lon": -97.7491626}, {"type": "node", "id": 860320196, "lat": 30.397777, "lon": -97.7471916}, {"type": "node", "id": 860320197, "lat": 30.3975306, "lon": -97.7472118}, {"type": "node", "id": 860320199, "lat": 30.3975157, "lon": -97.746966}, {"type": "node", "id": 860320201, "lat": 30.3977249, "lon": -97.7469489}, {"type": "node", "id": 860320203, "lat": 30.3977477, "lon": -97.7469205}, {"type": "node", "id": 860320205, "lat": 30.3977899, "lon": -97.746966}, {"type": "node", "id": 860320207, "lat": 30.3977651, "lon": -97.7469969}, {"type": "node", "id": 1249567872, "lat": 30.3998084, "lon": -97.746813, "tags": {"amenity": "restaurant", "brand": "Gatti's Pizza", "brand:wikidata": "Q5527509", "brand:wikipedia": "en:Gatti's Pizza", "cuisine": "pizza", "name": "Gatti's Pizza"}}, {"type": "node", "id": 1249567906, "lat": 30.3999414, "lon": -97.7485126, "tags": {"amenity": "restaurant", "cuisine": "japanese", "name": "Fujiyama"}}, {"type": "node", "id": 1249567944, "lat": 30.3987013, "lon": -97.7491029, "tags": {"amenity": "cafe", "name": "Yogertz"}}, {"type": "node", "id": 1249568695, "lat": 30.3999342, "lon": -97.7483653, "tags": {"amenity": "cafe", "name": "Great Harvest Bread Co."}}, {"type": "node", "id": 2530278181, "lat": 30.4019782, "lon": -97.7469768, "tags": {"amenity": "cafe", "name": "Signature Cafe"}}, {"type": "node", "id": 2530278183, "lat": 30.401983, "lon": -97.7468743, "tags": {"amenity": "cafe", "brand": "Starbucks", "brand:wikidata": "Q37158", "brand:wikipedia": "en:Starbucks", "contact:website": "https://www.starbucks.com/store-locator/store/15485/hwy-183-braker-ln-randalls-10900-research-blvd-austin-tx-787595722-us", "cuisine": "coffee_shop", "name": "Starbucks", "official_name": "Starbucks Coffee", "takeaway": "yes"}}, {"type": "node", "id": 3864436061, "lat": 30.398259, "lon": -97.7493286, "tags": {"addr:city": "Austin", "addr:housenumber": "10710", "addr:state": "TX", "addr:street": "Research Boulevard", "addr:unit": "328", "amenity": "restaurant", "cuisine": "asian", "delivery": "yes", "name": "Mama Fu's", "opening_hours": "Su-Th 11:00-21:00; Fr-Sa 11:00-22:00", "takeaway": "yes"}}, {"type": "node", "id": 8067249790, "lat": 30.39667, "lon": -97.749383}, {"type": "node", "id": 8067249791, "lat": 30.3966677, "lon": -97.7493483}, {"type": "way", "id": 72378709, "nodes": [859657438, 859657439, 859657441, 8067249790, 8067249791, 859657446, 859657447, 859657449, 859657450, 859657451, 859657438], "tags": {"addr:city": "Austin", "addr:housenumber": "10201", "addr:postcode": "78759", "addr:state": "TX", "addr:street": "Jollyville Road", "alt_name": "Manuel;Manuels;Manuel\u2019s", "amenity": "restaurant", "building": "yes", "cuisine": "mexican", "name": "Manuel's"}}, {"type": "way", "id": 72463808, "nodes": [860320201, 860320203, 860320205, 860320207, 860320196, 860320197, 860320199, 860320201], "tags": {"addr:housenumber": "10614", "addr:postcode": "78759", "addr:street": "Research Boulevard", "amenity": "restaurant", "brand": "Saltgrass Steak House", "brand:wikidata": "Q7406113", "brand:wikipedia": "en:Saltgrass Steak House", "building": "yes", "cuisine": "steak_house", "name": "Saltgrass Steak House"}}]}